Workbook

Sheet Budget
A1: items | B1: jan | C1: Feb | D1: Mar | E1: apr | F1: may | G1: jun | H1: July | I1: Aug | J1: Sept | K1: Oct | L1: Nov | M1: Dec | N1: Total
A2: Income | B2: =Items!D2 -> 7543.02 | N2: =sum(B2:M2) -> 7543.02
N3: =sum(B3:M3) -> 0
A4: Life Insurance | B4: =Items!D86 -> 912.59 | N4: =sum(B4:M4) -> 912.59
A5: Cash App | B5: =Items!D14 -> 341 | H5: =SUM(D5+E5+F5+G5) -> 0 | N5: =sum(B5:M5) -> 341
A6: Car payment | B6: =Items!D25 -> 510 | H6: =SUM(D6+E6+F6+G6) -> 0 | N6: =sum(B6:M6) -> 510
A7: Car Insurance | B7: =Items!D79 -> 325.25 | H7: =SUM(D7+E7+F7+G7) -> 0 | N7: =sum(B7:M7) -> 325.25
A8: Child support | B8: =Items!D27 -> 600 | H8: =SUM(D8+E8+F8+G8) -> 0 | N8: =sum(B8:M8) -> 600
A9: Fitness | B9: =Items!D37 -> 23.06 | H9: =SUM(D9+E9+F9+G9) -> 0 | N9: =sum(B9:M9) -> 23.06
A10: Food | B10: =Items!D39 -> 208.04 | H10: =SUM(D10+E10+F10+G10) -> 0 | N10: =sum(B10:M10) -> 208.04
A11: Gas | B11: =Items!D67 -> 207.68 | H11: =SUM(D11+E11+F11+G11) -> 0 | N11: =sum(B11:M11) -> 207.68
A12: Haircut | B12: =Items!D83 -> 82.5 | H12: =SUM(D12+E12+F12+G12) -> 0 | N12: =Items!D83 -> 82.5
A13: Bank fee | B13: =Items!D10 -> 4.95 | H13: =SUM(D13+E13+F13+G13) -> 0 | N13: =sum(B13:M13) -> 4.95
A14: Internet & mobile | B14: =Items!D75 -> 63.35 | H14: =SUM(D14+E14+F14+G14) -> 0 | N14: =sum(B14:M14) -> 63.35
A15: Legal | B15: =Items!D77 -> 49 | H15: =SUM(D15+E15+F15+G15) -> 0 | N15: =sum(B15:M15) -> 49
A16: Membership | B16: =Items!D89 -> 149.97 | H16: =SUM(D16+E16+F16+G16) -> 0 | N16: =sum(B16:M16) -> 149.97
A17: Mortagage | B17: =Items!D91 -> 2600 | H17: =SUM(D17+E17+F17+G17) -> 0 | N17: =sum(B17:M17) -> 2600
A18: Mobile | B18: =Items!D94 -> 92.16 | N18: =Items!D94 -> 92.16
A19: Other | B19: =Items!D97 -> 511.76 | N19: =sum(B19:M19) -> 511.76
A20: Phone | B20: =Items!D102 -> 180 | H20: =SUM(D20+E20+F20+G20) -> 0 | N20: =sum(B20:M20) -> 180
A21: Saving fee | B21: =Items!D33 -> 2.97 | N21: =sum(B21:M21) -> 2.97
A22: Subscription | B22: =Items!D120 -> 324.21 | N22: =sum(B22:M22) -> 324.21
A23: Union dues | B23: =Items!D137 -> 201 | H23: =SUM(D23+E23+F23+G23) -> 0 | N23: =Items!D138 -> 201
A24: Cash App | B24: =Items!D14 -> 341 | N24: =sum(B24:M24) -> 341
A25: Saving | B25: =Items!D107 -> 166.73 | N25: =sum(B25:M25) -> 166.73
A26: Retail | B26: =Items!D104 -> 43 | N26: =sum(B26:M26) -> 43
A27: Tolls | B27: =Items!D130 -> 120 | N27: =sum(B27:M27) -> 120
A28: Monthly debt | B28: =sum(B4:B27) -> 8060.22 | N28: =sum(B28:M28) -> 8060.22
M31: Income | N31: =N2 -> 7543.02
M32: Debt | N32: =sum(N3:N27) -> 8060.22
N33: =sum(N31-N32) -> -517.2

Sheet Items
A1: Date | B1: Description | C1: Item | D1: Cost
A2: Income | D2: =sum(D3:D9) -> 7543.02 | E2: =sum(E3:E9) -> 0
A3: 46022 | B3: Income | C3: Direct Deposit | D3: 1100.22
A4: 45665 | B4: Income | C4: Direct Deposit | D4: 733.47
A5: 46037 | B5: Income | C5: Direct Deposit | D5: 1466.95
A6: 46044 | B6: Income | C6: Direct Deposit | D6: 1833.69
A7: 46050 | B7: Income | C7: Direct Deposit | D7: 1833.69
B8: Income | C8: Firestyle llc | D8: 575
A10: Bank Fee | D10: =D11 -> 4.95 | E10: =E11
A11: 46038 | B11: Banking Fee | C11: Maintenance Fee | D11: 4.95
A12: 46038 | B12: Bank fee | C12: Atm fee | D12: 2.5
A13: 46049 | B13: Bank fee | C13: Atm fee | D13: 2.5
A14: Cash App | D14: =SUM(D15:D24) -> 341 | E14: =SUM(E15:E24) -> 0
A15: 46027 | B15: Cash App | C15: Derrell Black Jr | D15: 10
A16: 46027 | B16: Cash App | C16: Derrell Black Jr | D16: 6
A17: 46027 | B17: Cash App | C17: Syron Smith | D17: 1
A18: 46027 | B18: Cash App | C18: James Moore | D18: 20
A19: 46028 | B19: Cash App | C19: Destiny | D19: 20
A20: 46034 | B20: Cash App | C20: Derrell Black jr | D20: 30
A21: 46037 | B21: Cash App | C21: Derrell Black jr | D21: 6
A22: 46041 | B22: Cash App | C22: Destiny | D22: 43
A23: 46045 | B23: Cash App | C23: James Moore | D23: 180
A24: 46046 | B24: cash app | C24: Derrell Black jr | D24: 25
A25: Car payment | D25: 510 | E25: 510
A26: 46037 | B26: Car payment | C26: Ally Finanacial | D26: =D25 -> 510
A27: Child support | D27: =sum(D28:D31) -> 600 | E27: =sum(E28:E31) -> 0
A28: 46028 | B28: Child support | C28: Expert pay | D28: 150
A29: 46042 | B29: Child support | C29: Expert Pay | D29: 150
A30: 46035 | B30: Child support | C30: Expert pay | D30: 150
A31: 46051 | B31: Child support | C31: Expert pay | D31: 150
A33: Fee | D33: =sum(D34:D36) -> 2.97
A34: 46027 | B34: Fee | C34: Opportun | D34: 0.99
A35: 46027 | B35: Fee | C35: Opportun | D35: 0.99
A36: 46044 | B36: Fee | C36: Opportun | D36: 0.99
A37: Fitness | D37: =D38 -> 23.06
A38: 46042 | B38: Fitness | C38: Plant Fitness | D38: 23.06
A39: Food | D39: =sum(D40:D60) -> 208.04
A40: 46024 | B40: Food | C40: Food truck | D40: 3.42
A41: 46024 | B41: Food | C41: Fox one | D41: 22.05
A42: 46027 | B42: Food | C42: Town & Country | D42: 11.25
A43: 46028 | B43: Food | C43: Food truck | D43: 5.69
A44: 46028 | B44: Food | C44: Town & Country | D44: 7.71
A45: 46030 | B45: Food | C45: Food truck | D45: 9.11
A46: 46030 | B46: food | C46: Dunkin' Donuts | D46: 4.79
A47: 46030 | B47: Food | C47: Town & Country | D47: 8.73
A48: 46034 | B48: Food | C48: Rosatis pizza | D48: 8.25
A49: 46034 | B49: Food | C49: Old fashion donuts | D49: 3.32
A50: 46034 | B50: food | C50: Sharks, fish, and chicken | D50: 24.06
A51: 46034 | B51: Food | C51: Town & Country | D51: 11.25
... A65: 46034 | B65: Food | C65: Town & Country | D65: 6.84
A67: Gas | D67: =sum(D68:D72) -> 207.68
A68: 46027 | B68: Gas | C68: BP | D68: 53.48
A69: 46030 | B69: Gas | C69: BP | D69: 44.89
A70: 45672 | B70: Gas | C70: BP | D70: 37.39
A71: 46041 | B71: Gas | C71: Bp | D71: 32.23
A72: 46044 | B72: Gas | C72: Bp | D72: 39.69
A73: 46050 | B73: Gas | C73: Bp | D73: 40.63
A74: 1/27/0226 | B74: Gas | C74: Bp | D74: 47.09
A75: Internet | D75: =D76 -> 63.35
A76: 46034 | B76: Internet | C76: Comcast internet | D76: 63.35
A77: Legal | D77: =D78 -> 49
A78: 46029 | B78: Legal | C78: Law depot | D78: 49
A79: Car insurance | D79: =sum(D80:D81) -> 325.25
A80: 46045 | B80: Car insurance | C80: Artisan and trucks | D80: 290
A81: Credit Card | D81: 35.25
A82: 46038 | B82: Credit card | C82: Credit one | D82: =D81 -> 35.25
A83: Haircut | D83: =SUM(D84:D85) -> 82.5
B84: Haircut | C84: Studio 9647 | D84: 40
A85: 46049 | B85: Haircut | C85: Studio 9647 | D85: 42.5
A86: Life Insurance | D86: =sum(D87:D88) -> 912.59
A87: 46041 | B87: Life Insurance | C87: Transamerican | D87: 801.66
A88: 46041 | B88: Life Insurance | C88: Transamerican | D88: 110.93
A89: membership | D89: =D90 -> 149.97
A90: 46034 | B90: membership | C90: MWR Financial | D90: 149.97
A91: Mortagage | D91: =sum(D92:D93) -> 2600
A92: 46023 | B92: Mortagage | C92: 10052 S Forest Ave | D92: 1300
A93: 46054 | B93: Mortagage | C93: 10052 S Forest Ave | D93: 1300
A94: Mobile | D94: =sum(D95:D96) -> 92.16
A95: 46034 | B95: Mobile | C95: Xfinity mobile | D95: 50
A96: 46034 | B96: Mobile | C96: Xfinity mobile | D96: 42.16
A97: Other | D97: =SUM(D98:D100) -> 511.76
A98: 46034 | B98: Other | C98: PMV Services | D98: 96.76
A99: 46045 | B99: Other | C99: Insurance | D99: 200
A100: 46045 | B100: Other | C100: Insurance | D100: 215
A101: Phone | D101: =D102 -> 180
A102: 46029 | B102: Phone | C102: Verizon | D102: 180
A103: retail | D103: =sum(D104:D106) -> 135
A104: 46031 | B104: retail | C104: Walmart | D104: 43
A105: 46044 | B105: Retail | C105: Walmart | D105: 43
A106: 46044 | B106: Retail | C106: Dtlr | D106: 49
A107: Saving | D107: =sum(D108:D117) -> 166.73
A108: 46027 | B108: Saving | C108: Oppotun | D108: 9.88
A109: 46035 | B109: Saving | C109: Opportun | D109: 5
A110: 46036 | B110: Saving | C110: Opportun | D110: 14.64
A111: 46036 | B111: Saving | C111: Opportun | D111: 24.47
A112: 46037 | B112: Saving | C112: Opportun | D112: 16.91
A113: 45671 | B113: Saving | C113: Opportun | D113: 0.05
A114: 46045 | B114: Saving | C114: Opportun | D114: 13.33
A115: 46051 | B115: Saving | C115: Opportun | D115: 41.07
A116: 46050 | B116: Saving | C116: Opportun | D116: 17.01
...

Sheet March
A1: Date | B1: Description | C1: Item | E1: Cost
A2: Bank Fee | E2: =E3 -> 4.95
A3: 46038 | B3: Banking Fee | C3: Maintenance Fee | E3: 4.95
A4: Cash App | E4: =SUM(E5:E10) -> 87
A5: 46027 | B5: Cash App | C5: Derrell Black Jr | E5: 10
A6: 46027 | B6: Cash App | C6: Derrell Black Jr | E6: 6
A7: 46027 | B7: Cash App | C7: Syron Smith | E7: 1
A8: 46027 | B8: Cash App | C8: James Moore | E8: 20
A9: 46028 | B9: Cash App | C9: Destiny | E9: 20
A10: 46034 | B10: Cash App | C10: Derrell Black jr | E10: 30
A11: Child support | E11: =sum(E12:E14) -> 450
A12: 46028 | B12: Child support | C12: Expert pay | E12: 150
A13: 46042 | B13: Child support | C13: Expert Pay | E13: 150
A14: 46035 | B14: Child support | C14: Expert pay | E14: 150
A15: Fee | E15: =sum(E16:E17) -> 1.98
A16: 46027 | B16: Fee | C16: Opportun | E16: 0.99
A17: 46027 | B17: Fee | C17: Opportun | E17: 0.99
A18: Food | E18: =sum(E19:E34) -> 174.1
A19: 46024 | B19: Food | C19: Food truck | E19: 3.42
A20: 46024 | B20: Food | C20: Fox one | E20: 22.05
A21: 46027 | B21: Food | C21: Town & Country | E21: 11.25
A22: 46028 | B22: Food | C22: Food truck | E22: 5.69
A23: 46028 | B23: Food | C23: Town & Country | E23: 7.71
A24: 46030 | B24: Food | C24: Food truck | E24: 9.11
A25: 46030 | B25: food | C25: Dunkin' Donuts | E25: 4.79
A26: 46030 | B26: Food | C26: Town & Country | E26: 8.73
A27: 46034 | B27: Food | C27: Rosatis pizza | E27: 8.25
A28: 46034 | B28: Food | C28: Old fashion donuts | E28: 3.32
A29: 46034 | B29: food | C29: Sharks, fish, and chicken | E29: 24.06
A30: 46034 | B30: Food | C30: Town & Country | E30: 11.25
... A34: 46036 | B34: Food | C34: Ricky Rocket | E34: 13.92
A35: Gas | E35: =sum(E36:E37) -> 98.37
A36: 46027 | B36: Gas | C36: BP | E36: 53.48
A37: 46030 | B37: Gas | C37: BP | E37: 44.89
A38: Internet | E38: =E39 -> 63.35
A39: 46034 | B39: Internet | C39: Comcast internet | E39: 63.35
A40: Legal | E40: =E41 -> 49
A41: 46029 | B41: Legal | C41: Law depot | E41: 49
A42: Car insurance | E42: =sum(E43:E44) -> 290
A43: 46045 | B43: Car insurance | C43: Artisan and trucks | E43: 290
A44: 46076 | B44: Car insurance | C44: Artisan and trucks
A45: Credit Card
A47: Life Insurance | E47: =sum(E48:E49) -> 912.59
A48: 46041 | B48: Life Insurance | C48: Transamerican | E48: 801.66
A49: 46041 | B49: Life Insurance | C49: Transamerican | E49: 110.93
A50: membership | E50: =E51 -> 149.97
A51: 46034 | B51: membership | C51: MWR Financial | E51: 149.97
A52: Mortagage | E52: =sum(E53:E54) -> 1300
A53: 46023 | B53: Mortagage | C53: 10052 S Forest Ave | E53: 1300
A54: 46054 | B54: Mortagage | C54: 10052 S Forest Ave
A55: Mobile | E55: =sum(E56:E57) -> 92.16
A56: 46034 | B56: Mobile | C56: Xfinity mobile | E56: 50
A57: 46034 | B57: Mobile | C57: Xfinity mobile | E57: 42.16
A58: Other | E58: =E59 -> 96.76
A59: 46034 | B59: Other | C59: PMV Services | E59: 96.76
A60: Phone | E60: =E61 -> 180
A61: 46029 | B61: Phone | C61: Verizon | E61: 180
A62: retail | E62: =E63 -> 43
A63: 46031 | B63: retail | C63: Walmart | E63: 43
A64: Saving | E64: =sum(E65:E67) -> 29.52
A65: 46027 | B65: Saving | C65: Oppotun | E65: 9.88
A66: 46035 | B66: Saving | C66: Opportun | E66: 5
A67: 46036 | B67: Saving | C67: Opportun | E67: 14.64
A68: subscription | E68: =sum(E69:E72) -> 282.34
A69: 46030 | B69: subscription | C69: Apple | E69: 13.22
A70: 46034 | B70: subscription | C70: Apple | E70: 21.93
A71: 46034 | B71: Subscription | C71: Apple | E71: 245
A72: 46027 | B72: Subscriptions | C72: Apple | E72: 2.19
A73: Tolls | E73: =sum(E74:E76) -> 60
A74: 46029 | B74: Tolls | C74: Tollway | E74: 20
A75: 46029 | B75: Tolls | C75: Tollway | E75: 20
A76: 46029 | B76: Tolls | C76: Tollway | E76: 20

Sheet  Feb
A1: Date | B1: Description | C1: Item | D1: Cost
A2: Income | D2: =SUM(D3:D6) -> 7333.28
B3: Direct deposit | C3: Livewire | D3: 1833.32
B4: Direct deposit | C4: Livewire | D4: 1833.32
B5: Direct deposit | C5: Livewire | D5: 1833.32
B6: Direct deposit | C6: Livewire | D6: 1833.32
A7: Bank Fee | D7: =D9
B9: Banking Fee | C9: Maintenance Fee
A10: Cash App | D10: =SUM(D11:D16) -> 0
B11: Cash App | C11: Derrell Black Jr
B12: Cash App | C12: Derrell Black Jr
B13: Cash App | C13: Syron Smith
B14: Cash App | C14: James Moore
B15: Cash App | C15: Destiny
B16: Cash App | C16: Derrell Black jr
A17: Child support | D17: =sum(D18:D20) -> 0
B18: Child support | C18: Expert pay
B19: Child support | C19: Expert Pay
B20: Child support | C20: Expert pay
A21: Fee | D21: =sum(D22:D23) -> 0
B22: Fee | C22: Opportun
B23: Fee | C23: Opportun
A24: Food | D24: =sum(D25:D39) -> 0
B25: Food | C25: Food truck
B26: Food | C26: Town & Country
B27: Food | C27: Food truck
B28: Food | C28: Town & Country
B29: Food | C29: Food truck
B30: food | C30: Dunkin' Donuts
B31: Food | C31: Town & Country
B32: Food | C32: Rosatis pizza
B33: Food | C33: Old fashion donuts
B34: food | C34: Sharks, fish, and chicken
B35: Food | C35: Town & Country
B36: Food | C36: Ricky Rocket
... B39: Food | C39: Ricky Rocket
A40: Gas | D40: =sum(D41:D42) -> 0
B41: Gas | C41: BP
B42: Gas | C42: BP
A43: Internet | D43: =D44
B44: Internet | C44: Comcast internet
A45: Legal | D45: =D46
B46: Legal | C46: Law depot
A47: Car insurance | D47: =sum(D48:D49) -> 0
B48: Car insurance | C48: Artisan and trucks
B49: Car insurance | C49: Artisan and trucks
A50: Credit Card
A52: Life Insurance | D52: =sum(D53:D54) -> 0
B53: Life Insurance | C53: Transamerican
B54: Life Insurance | C54: Transamerican
A55: membership | D55: =D56
B56: membership | C56: MWR Financial
A57: Mortagage | D57: =sum(D58:D59) -> 0
B58: Mortagage | C58: 10052 S Forest Ave
B59: Mortagage | C59: 10052 S Forest Ave
A60: Mobile | D60: =sum(D61:D62) -> 0
B61: Mobile | C61: Xfinity mobile
B62: Mobile | C62: Xfinity mobile
A63: Other | D63: =D64
B64: Other | C64: PMV Services
A65: Phone | D65: =D66
B66: Phone | C66: Verizon
A67: retail | D67: =D68
B68: retail | C68: Walmart
A69: Saving | D69: =sum(D70:D72) -> 0
B70: Saving | C70: Oppotun
B71: Saving | C71: Opportun
B72: Saving | C72: Opportun
A73: subscription | D73: =sum(D74:D77) -> 0
B74: subscription | C74: Apple
B75: subscription | C75: Apple
B76: Subscription | C76: Apple
B77: Subscriptions | C77: Apple
A78: Tolls | D78: =sum(D79:D81) -> 0
B79: Tolls | C79: Tollway
B80: Tolls | C80: Tollway
B81: Tolls | C81: Tollway
